flowroute/__init__.py
flowroute/configuration.py
flowroute/controller.py
flowroute/exception.py
flowroute/helper.py
flowroute/message.py
flowroute_messaging_fossum-0.2.0.dist-info/LICENSE
flowroute_messaging_fossum-0.2.0.dist-info/METADATA
flowroute_messaging_fossum-0.2.0.dist-info/WHEEL
flowroute_messaging_fossum-0.2.0.dist-info/top_level.txt
flowroute_messaging_fossum-0.2.0.dist-info/RECORD
